algogames/Chess.py
algogames/DuelSnakes.py
algogames/Snake.py
algogames/TenTen.py
algogames/TicTacToe.py
algogames/__init__.py
algogames/base.py
algogames-0.0.1.dist-info/METADATA
algogames-0.0.1.dist-info/WHEEL
algogames-0.0.1.dist-info/licenses/LICENSE
algogames-0.0.1.dist-info/RECORD
